flying_discs/__init__.py
flying_discs/py.typed
flying_discs/utils.py
flying_discs/frispy/__init__.py
flying_discs/frispy/base.py
flying_discs/frispy/constants.py
flying_discs/frispy/coordinates.py
flying_discs/morrison/__init__.py
flying_discs/morrison/base.py
flying_discs/morrison/bezier.py
flying_discs/morrison/constants.py
flying_discs/morrison/coordinates.py
flying_discs/morrison/linear.py
flying_discs-0.4.0.dist-info/METADATA
flying_discs-0.4.0.dist-info/WHEEL
flying_discs-0.4.0.dist-info/licenses/LICENSE
flying_discs-0.4.0.dist-info/RECORD
