Metadata-Version: 2.3
Name: flying-discs
Version: 0.4.0
Summary: Implementation of physical models for flying sport discs.
Project-URL: Source, https://github.com/crzdg/flying-discs
Author: Reto Barmettler
License-Expression: LGPL-3.0-only
License-File: LICENSE
Classifier: Development Status :: 3 - Alpha
Classifier: Operating System :: OS Independent
Classifier: Programming Language :: Python :: 3 :: Only
Classifier: Programming Language :: Python :: 3.9
Classifier: Programming Language :: Python :: 3.10
Classifier: Programming Language :: Python :: 3.11
Requires-Python: >=3.9
Requires-Dist: frispy
Requires-Dist: numpy>=1.22.0
Provides-Extra: ci
Requires-Dist: genbadge[all]; extra == 'ci'
Requires-Dist: hatch; extra == 'ci'
Requires-Dist: hatch-regex-commit; extra == 'ci'
Provides-Extra: dev
Requires-Dist: hatch; extra == 'dev'
Provides-Extra: jupyter
Requires-Dist: jupyter; extra == 'jupyter'
Requires-Dist: matplotlib; extra == 'jupyter'
Provides-Extra: lint
Requires-Dist: pylint; extra == 'lint'
Provides-Extra: style
Requires-Dist: black; extra == 'style'
Requires-Dist: isort; extra == 'style'
Provides-Extra: test
Requires-Dist: pytest; extra == 'test'
Requires-Dist: pytest-cov; extra == 'test'
Requires-Dist: pytest-mock; extra == 'test'
Provides-Extra: type
Requires-Dist: mypy; extra == 'type'
Requires-Dist: types-pyyaml; extra == 'type'
